fuzzy_logic/__init__.py
fuzzy_logic/anfis.py
fuzzy_logic/clustering.py
fuzzy_logic/generic_fs.py
fuzzy_logic/mamdani_fs.py
fuzzy_logic/mf.py
fuzzy_logic/rule_parser.py
fuzzy_logic/rules.py
fuzzy_logic/sugeno_fs.py
fuzzy_logic/terms.py
fuzzy_logic/transform.py
fuzzy_logic/types.py
fuzzy_logic/variables.py
tests/__init__.py
tests/mf_test.py
fuzzy_logic_toolbox-1.0.2.dist-info/LICENSE
fuzzy_logic_toolbox-1.0.2.dist-info/METADATA
fuzzy_logic_toolbox-1.0.2.dist-info/WHEEL
fuzzy_logic_toolbox-1.0.2.dist-info/top_level.txt
fuzzy_logic_toolbox-1.0.2.dist-info/RECORD
