Metadata-Version: 2.1
Name: fuzzy-logic-toolbox
Version: 1.0.2
Summary: Fuzzy logic tool box as matlab
Home-page: https://github.com/Luferov/FuzzyLogicToolBox
Author: Luferov V.S.
Author-email: lyferov@yandex.ru
License: UNKNOWN
Platform: any
Requires-Python: >=3.7
Requires-Dist: numpy (>=1.18.2)
